Metadata-Version: 2.1
Name: record-redis
Version: 1.0.0
Summary: Provides caching of records using Redis
Home-page: https://ouroboroscoding.com/record-redis
Author: Chris Nasr - Ouroboros Coding Inc.
Author-email: chris@ouroboroscoding.com
License: MIT
Project-URL: Documentation, https://ouroboroscoding.com/record-redis
Project-URL: Source, https://github.com/ouroboroscoding/record-redis-python
Project-URL: Tracker, https://github.com/ouroboroscoding/record-redis-python/issues
Keywords: data,define,cache,record
Platform: UNKNOWN
Requires-Python: >=3.10
License-File: LICENSE
